msp430/__init__.py
msp430/commandline_helper.py
msp430/downloader.py
msp430/ram_usage.py
msp430/target.py
msp430/tool.py
msp430/asm/__init__.py
msp430/asm/as.py
msp430/asm/cpp.py
msp430/asm/disassemble.py
msp430/asm/forth.py
msp430/asm/h2forth.py
msp430/asm/infix2postfix.py
msp430/asm/ld.py
msp430/asm/lib.py
msp430/asm/mcu_definition_parser.py
msp430/asm/peripherals.py
msp430/asm/rpn.py
msp430/asm/definitions/msp430-mcu-list.txt
msp430/bsl/BL_150S_14x.txt
msp430/bsl/BL_150S_44x.txt
msp430/bsl/BS_150S_14x.txt
msp430/bsl/__init__.py
msp430/bsl/__main__.py
msp430/bsl/bsl.py
msp430/bsl/patch.txt
msp430/bsl/target/__init__.py
msp430/bsl/target/__main__.py
msp430/bsl/target/fcdprog.py
msp430/bsl/target/telosb.py
msp430/bsl5/RAM_BSL.00.06.05.34.txt
msp430/bsl5/__init__.py
msp430/bsl5/bsl5.py
msp430/bsl5/hid.py
msp430/bsl5/uart.py
msp430/gdb/__init__.py
msp430/gdb/__main__.py
msp430/gdb/gdb.py
msp430/gdb/target.py
msp430/jtag/HIL.py
msp430/jtag/__init__.py
msp430/jtag/__main__.py
msp430/jtag/clock.py
msp430/jtag/dco.py
msp430/jtag/hilspi.py
msp430/jtag/jtag.py
msp430/jtag/profile.py
msp430/jtag/target.py
msp430/legacy/__init__.py
msp430/legacy/bsl.py
msp430/legacy/bsl_main.py
msp430/legacy/jtag.py
msp430/listing/__init__.py
msp430/listing/iar.py
msp430/listing/mspgcc.py
msp430/memory/__init__.py
msp430/memory/bin.py
msp430/memory/compare.py
msp430/memory/convert.py
msp430/memory/elf.py
msp430/memory/error.py
msp430/memory/generate.py
msp430/memory/hexdump.py
msp430/memory/intelhex.py
msp430/memory/titext.py
msp430/shell/__init__.py
msp430/shell/command.py
msp430/shell/watch.py
python_msp430_tools-0.9.2.dist-info/DESCRIPTION.rst
python_msp430_tools-0.9.2.dist-info/METADATA
python_msp430_tools-0.9.2.dist-info/RECORD
python_msp430_tools-0.9.2.dist-info/WHEEL
python_msp430_tools-0.9.2.dist-info/entry_points.txt
python_msp430_tools-0.9.2.dist-info/metadata.json
python_msp430_tools-0.9.2.dist-info/top_level.txt
