Metadata-Version: 2.0
Name: python-msp430-tools
Version: 0.9.2
Summary: Python MSP430 Tools
Home-page: https://github.com/zsquareplusc/python-msp430-tools
Author: Chris Liechti
Author-email: cliechti@gmx.net
License: Simplified BSD License
Platform: UNKNOWN
Classifier: Development Status :: 4 - Beta
Classifier: Intended Audience :: Developers
Classifier: Intended Audience :: End Users/Desktop
Classifier: License :: OSI Approved :: BSD License
Classifier: Natural Language :: English
Classifier: Operating System :: OS Independent
Classifier: Programming Language :: Python
Classifier: Topic :: Software Development :: Embedded Systems
Classifier: Topic :: Software Development :: Assemblers
Classifier: Topic :: Software Development :: Libraries
